sic/__init__.py
sic/core.c
sic/core.cp38-win_amd64.pyd
sic/core.py
sic/implicit.c
sic/implicit.cp38-win_amd64.pyd
sic/implicit.py
sic/tokenizer.greek.xml
sic/tokenizer.standard.xml
sic/tokenizer.western.xml
sic-1.3.3.dist-info/LICENSE
sic-1.3.3.dist-info/METADATA
sic-1.3.3.dist-info/WHEEL
sic-1.3.3.dist-info/top_level.txt
sic-1.3.3.dist-info/RECORD
